cloudinteractive_ai_insights/azure_api.py
cloudinteractive_ai_insights/credentialprovider.py
cloudinteractive_ai_insights/document.py
cloudinteractive_ai_insights/main.py
cloudinteractive_ai_insights/openai_api.py
cloudinteractive_ai_insights/tasks.py
cloudinteractive_ai_insights-1.0.5.dist-info/METADATA
cloudinteractive_ai_insights-1.0.5.dist-info/WHEEL
cloudinteractive_ai_insights-1.0.5.dist-info/entry_points.txt
cloudinteractive_ai_insights-1.0.5.dist-info/top_level.txt
cloudinteractive_ai_insights-1.0.5.dist-info/RECORD
