Metadata-Version: 2.1
Name: cloudinteractive-ai-insights
Version: 1.0.5
Summary: Collection of AI tools designed to assist with your assignments and projects.
Home-page: https://github.com/Coppermine-SP/cloudinteractive-ai-insights
Author: CoppermineSP
Author-email: copperminesp@cloudinteractive.net
License: MIT
Classifier: Programming Language :: Python :: 3.9
Classifier: Programming Language :: Python :: 3.10
Classifier: Programming Language :: Python :: 3.11
Requires-Python: >=3.9
Requires-Dist: azure-cognitiveservices-vision-computervision
Requires-Dist: openai
Requires-Dist: pdf2image
Requires-Dist: tiktoken
